[{"type": "node", "id": 942928849, "lat": 53.5931485, "lon": 9.9437272, "tags": {"addr:city": "Hamburg", "addr:country": "DE", "addr:housenumber": "45", "addr:postcode": "22529", "addr:street": "Koppelstra\u00dfe", "amenity": "fast_food", "check_date:opening_hours": "2024-09-12", "cuisine": "kebab", "diet:vegan": "no", "diet:vegetarian": "yes", "indoor_seating": "yes", "name": "Kebap Lounge", "opening_hours": "Mo-Su 10:00-22:30", "outdoor_seating": "yes", "takeaway": "yes"}}, {"type": "way", "id": 37572043, "center": {"lat": 53.5930685, "lon": 9.9444322}, "nodes": [440308595, 6501256938, 440308598, 955712209, 955712207, 440308601, 7688416641, 7688416642, 1577077132, 6501260785, 440308595], "tags": {"addr:city": "Hamburg", "addr:country": "DE", "addr:housenumber": "47-49", "addr:postcode": "22529", "addr:street": "Koppelstra\u00dfe", "brand": "EDEKA", "brand:wikidata": "Q701755", "brand:wikipedia": "de:Edeka", "building": "retail", "building:levels": "1", "check_date": "2024-12-12", "email": "info@edeka-berndt.de", "name": "EDEKA Berndt", "opening_hours": "Mo-Fr 07:00-20:00; Sa 08:00-20:00; PH off", "operator": "Christian Berndt", "phone": "+49 40 564635", "roof:levels": "0", "roof:shape": "flat", "shop": "supermarket", "website": "https://edeka-berndt.de", "wheelchair": "yes"}}]